osbot_prefect/__init__.py
osbot_prefect/flows/Flow_Events__To__Prefect_Server.py
osbot_prefect/flows/__init__.py
osbot_prefect/server/Prefect__Artifacts.py
osbot_prefect/server/Prefect__Cloud_API.py
osbot_prefect/server/Prefect__Rest_API.py
osbot_prefect/server/Prefect__States.py
osbot_prefect/server/__init__.py
osbot_prefect/testing/Temp__Flow.py
osbot_prefect/testing/Temp__Flow_Run.py
osbot_prefect/testing/Temp__Task_Run.py
osbot_prefect/testing/__init__.py
osbot_prefect/utils/Version.py
osbot_prefect/utils/__init__.py
osbot_prefect/utils/for__osbot_aws.py
osbot_prefect/version
osbot_prefect-0.2.10.dist-info/LICENSE
osbot_prefect-0.2.10.dist-info/METADATA
osbot_prefect-0.2.10.dist-info/WHEEL
osbot_prefect-0.2.10.dist-info/RECORD
