Metadata-Version: 2.1
Name: osbot_prefect
Version: 0.2.10
Summary: OWASP Security Bot - Prefect
Home-page: https://github.com/owasp-sbot/OSBot-Prefect
License: MIT
Author: Dinis Cruz
Author-email: dinis.cruz@owasp.org
Requires-Python: >=3.11,<4.0
Classifier: License :: OSI Approved :: MIT License
Classifier: Programming Language :: Python :: 3
Classifier: Programming Language :: Python :: 3.11
Classifier: Programming Language :: Python :: 3.12
Classifier: Programming Language :: Python :: 3.13
Requires-Dist: osbot-utils
Project-URL: Repository, https://github.com/owasp-sbot/OSBot-Prefect
